qt_icon_browser/__init__.py
qt_icon_browser-1.0.1.dist-info/entry_points.txt
qt_icon_browser-1.0.1.dist-info/LICENSE
qt_icon_browser-1.0.1.dist-info/WHEEL
qt_icon_browser-1.0.1.dist-info/METADATA
qt_icon_browser-1.0.1.dist-info/RECORD
