Metadata-Version: 2.1
Name: qt_icon_browser
Version: 1.0.1
Summary: Displays all possible built-in (theme) icons.
Author-email: Leon Dionne <ldionne@dridesign.sh.cn>
Classifier: License :: OSI Approved :: GNU General Public License v3 or later (GPLv3+)
Requires-Dist: PyQt5 >= 5.0.0
Project-URL: Home, https://github.com/Zen-Master-SoSo/qt_icon_browser
